grz/grz.py
grz/CommandCollector/Collector.py
grz/CommandCollector/__init__.py
grz/CommandParser/Parser.py
grz/CommandParser/__init__.py
grz/ErrorHandler/Handler.py
grz/ErrorHandler/__init__.py
grz-1.2.0.dist-info/LICENSE.html
grz-1.2.0.dist-info/METADATA
grz-1.2.0.dist-info/WHEEL
grz-1.2.0.dist-info/entry_points.txt
grz-1.2.0.dist-info/top_level.txt
grz-1.2.0.dist-info/RECORD
