Metadata-Version: 2.1
Name: grz
Version: 1.2.0
Summary: This is a widget designed for openGauss Database inspection Tool!
Author: RuiXu
Author-email: RuiXu <ruixu@std.uestc.edu.cn>
License: License: GPL version 3, excluding DRM provisions
Classifier: Programming Language :: Python :: 3
Classifier: License :: OSI Approved :: GNU General Public License v3 (GPLv3)
Requires-Python: >=3.6
License-File: LICENSE.html
